pika_sdk/__init__.py
pika_sdk/exceptions.py
pika_sdk/sdk.py
pika_sdk-0.2.1.dist-info/LICENSE
pika_sdk-0.2.1.dist-info/METADATA
pika_sdk-0.2.1.dist-info/WHEEL
pika_sdk-0.2.1.dist-info/top_level.txt
pika_sdk-0.2.1.dist-info/RECORD
