Metadata-Version: 2.1
Name: pika-sdk
Version: 0.2.1
Summary: Pika API python SDK.
Author-email: Rishi Mohan <iamrishi.ms@gmail.com>
License: MIT License
Project-URL: Homepage, https://pika.style/image-generation-api
Classifier: License :: OSI Approved :: MIT License
Classifier: Programming Language :: Python
Classifier: Programming Language :: Python :: 3
Requires-Python: >=3.6
License-File: LICENSE
Requires-Dist: requests >=2.28.1
